rtl/tlb_unit.sv
import mmu_pkg::*;

module tlb_unit(
    input  logic iclk,
    input  logic irst_n,

    // lookup path
    input  logic lookup_valid,
    input  logic [VPN_WIDTH-1:0] lookup_vpn,

    output logic hit,
    output logic miss,
    output logic [PPN_WIDTH-1:0] return_ppn,
    output logic [TLB_INDEX_WIDTH-1:0] hit_idx,

    // refill path (from page walker)
    input  logic refill_valid,
    input  logic [VPN_WIDTH-1:0] refill_vpn,
    input  logic [PPN_WIDTH-1:0] refill_ppn
);

    logic valid_array[TLB_ENTRIES];
    logic [VPN_WIDTH-1:0] vpn_array[TLB_ENTRIES];
    logic [PPN_WIDTH-1:0] ppn_array[TLB_ENTRIES];
    integer i;

    logic [TLB_ENTRIES-1:0] match;
    logic [PPN_WIDTH-1:0] tmp_ppn;
    logic [TLB_INDEX_WIDTH-1:0] repl_ptr;
    logic found_match;

    // Refill logic
    always @(posedge iclk or negedge irst_n) begin
        if (!irst_n) begin
            for (i = 0; i < TLB_ENTRIES; i = i + 1) begin
                valid_array[i] <= 1'b0;
                vpn_array[i]   <= {VPN_WIDTH{1'b0}};
                ppn_array[i]   <= {PPN_WIDTH{1'b0}};
            end
            repl_ptr <= {TLB_INDEX_WIDTH{1'b0}};
        end else if (refill_valid) begin
            valid_array[repl_ptr] <= 1'b1;
            vpn_array[repl_ptr]   <= refill_vpn;
            ppn_array[repl_ptr]   <= refill_ppn;
            repl_ptr <= repl_ptr + 1;
        end
    end

    // CAM-style lookup: compare all TLB entries in parallel
    always @* begin
        hit_idx = {TLB_INDEX_WIDTH{1'b0}};
        tmp_ppn = {PPN_WIDTH{1'b0}};
        found_match = 1'b0;

        for (i = 0; i < TLB_ENTRIES; i = i + 1) begin
            match[i] = lookup_valid && valid_array[i] && (vpn_array[i] == lookup_vpn);
        end

        if (lookup_valid) begin
            for (i = 0; i < TLB_ENTRIES; i = i + 1) begin
                if (match[i] && !found_match) begin
                    hit_idx = i;
                    tmp_ppn = ppn_array[i];
                    found_match = 1'b1;
                end
            end
        end
    end

    assign hit  = lookup_valid && |match;
    assign miss = lookup_valid && ~|match;
    assign return_ppn = tmp_ppn;

endmodule

tb/tlb/tlb_tb.sv
`timescale 1ns/1ps
import mmu_pkg::*;

module tlb_tb;

    logic iclk = 0;
    logic irst_n = 0;

    logic lookup_valid;
    logic [VPN_WIDTH-1:0] lookup_vpn;

    logic hit;
    logic miss;
    logic [PPN_WIDTH-1:0] return_ppn;
    logic [TLB_INDEX_WIDTH-1:0] hit_idx;

    logic refill_valid;
    logic [VPN_WIDTH-1:0] refill_vpn;
    logic [PPN_WIDTH-1:0] refill_ppn;

    tlb_unit uut (
        .iclk(iclk),
        .irst_n(irst_n),
        .lookup_valid(lookup_valid),
        .lookup_vpn(lookup_vpn),
        .hit(hit),
        .miss(miss),
        .return_ppn(return_ppn),
        .hit_idx(hit_idx),
        .refill_valid(refill_valid),
        .refill_vpn(refill_vpn),
        .refill_ppn(refill_ppn)
    );

    always #5 iclk = ~iclk;

    initial begin
        $dumpfile("tb/waveforms/tlb_tb.vcd");
        $dumpvars(0, tlb_tb);

        // Reset
        irst_n = 0;
        lookup_valid = 0;
        refill_valid = 0;
        refill_vpn = '0;
        refill_ppn = '0;
        lookup_vpn = '0;
        #20;
        irst_n = 1;
        #10;

        // Refill a single entry
        refill_valid = 1;
        refill_vpn = 32'h0000_000A >> PAGE_OFFSET_BITS; // low VPN
        refill_ppn = 32'h0000_00AA >> PAGE_OFFSET_BITS;
        #10;
        refill_valid = 0;
        refill_vpn = '0;
        refill_ppn = '0;
        #10;

        // Lookup the same VPN: should hit
        lookup_valid = 1;
        lookup_vpn = 32'h0000_000A >> PAGE_OFFSET_BITS;
        #10;
        lookup_valid = 0;
        #10;

        // Lookup a different VPN: should miss
        lookup_valid = 1;
        lookup_vpn = 32'h0000_000B >> PAGE_OFFSET_BITS;
        #10;
        lookup_valid = 0;
        #10;

        // Refill a second entry and then lookup both
        refill_valid = 1;
        refill_vpn = 32'h0000_000C >> PAGE_OFFSET_BITS;
        refill_ppn = 32'h0000_00BB >> PAGE_OFFSET_BITS;
        #10;
        refill_valid = 0;
        #10;

        lookup_valid = 1;
        lookup_vpn = 32'h0000_000C >> PAGE_OFFSET_BITS;
        #10;
        lookup_valid = 0;
        #10;

        $display("TLB test complete: hit=%0b miss=%0b hit_idx=%0d return_ppn=%h", hit, miss, hit_idx, return_ppn);
        #20;
        $finish;
    end

endmodule

tb/waveforms/tlb_tb.vcd
$date
	Sun Jun 14 15:01:58 2026
$end
$version
	Icarus Verilog
$end
$timescale
	1ps
$end
$scope module tlb_tb $end
$var wire 20 ! return_ppn [19:0] $end
$var wire 1 " miss $end
$var wire 4 # hit_idx [3:0] $end
$var wire 1 $ hit $end
$var reg 1 % iclk $end
$var reg 1 & irst_n $end
$var reg 1 ' lookup_valid $end
$var reg 20 ( lookup_vpn [19:0] $end
$var reg 20 ) refill_ppn [19:0] $end
$var reg 1 * refill_valid $end
$var reg 20 + refill_vpn [19:0] $end
$scope module uut $end
$var wire 1 $ hit $end
$var wire 1 % iclk $end
$var wire 1 & irst_n $end
$var wire 1 ' lookup_valid $end
$var wire 20 , lookup_vpn [19:0] $end
$var wire 1 " miss $end
$var wire 20 - refill_ppn [19:0] $end
$var wire 1 * refill_valid $end
$var wire 20 . refill_vpn [19:0] $end
$var wire 20 / return_ppn [19:0] $end
$var reg 1 0 found_match $end
$var reg 4 1 hit_idx [3:0] $end
$var reg 16 2 match [15:0] $end
$var reg 4 3 repl_ptr [3:0] $end
$var reg 20 4 tmp_ppn [19:0] $end
$var integer 32 5 i [31:0] $end
$upscope $end
$upscope $end
$enddefinitions $end
$comment Show the parameter values. $end
$dumpall
$end
#0
$dumpvars
b10000 5
b0 4
bx 3
bx 2
b0 1
00
b0 /
b0 .
b0 -
b0 ,
b0 +
0*
b0 )
b0 (
0'
0&
0%
0$
b0 #
0"
b0 !
$end
#5000
b0 2
b0 3
b10000 5
1%
#10000
0%
#15000
b10000 5
1%
#20000
0%
1&
#25000
1%
#30000
0%
1*
#35000
b1 2
b10000 5
b1 3
1%
#40000
0%
0*
#45000
1%
#50000
1$
10
b10000 5
0%
1'
#55000
1%
#60000
0$
b10000 5
00
0%
0'
#65000
1%
#70000
1$
10
b10000 5
0%
1'
#75000
1%
#80000
0$
b10000 5
00
0%
0'
#85000
1%
#90000
0%
1*
#95000
b11 2
b10000 5
b10 3
1%
#100000
0%
0*
#105000
1%
#110000
1$
10
b10000 5
0%
1'
#115000
1%
#120000
0$
b10000 5
00
0%
0'
